logs/__init__.py
qalab/__init__.py
qalab/qaenv.py
qalab/apks/__init__.py
qalab/configs/__init__.py
qalab/configs/settings.py
qalab/core/__init__.py
qalab/core/server_driver_appium.py
qalab/core/server_driver_base.py
qalab/core/server_driver_selenium.py
qalab/drivers/__init__.py
qalaboratory-0.2.0.data/scripts/qaenv.py
qalaboratory-0.2.0.dist-info/LICENSE
qalaboratory-0.2.0.dist-info/METADATA
qalaboratory-0.2.0.dist-info/WHEEL
qalaboratory-0.2.0.dist-info/top_level.txt
qalaboratory-0.2.0.dist-info/RECORD
