Metadata-Version: 2.1
Name: qalaboratory
Version: 0.2.0
Summary: QALAB, proyect manager for QA open source proyects, managing selenium, appium, selendroid drivers
Home-page: https://github.com/netzulo/qalab
Author: Netzulo Open Source
Author-email: netzuleando@gmail.com
License: UNKNOWN
Download-URL: https://github.com/netzulo/qalab/tarball/v0.2.0
Keywords: testing,logging,functional,selenium,test,installer,hub,node,qa,driver,chrome,firefox,phantomjs,iexplorer,edge,appium,mobile,selendroid,automation,pytest
Platform: UNKNOWN
Classifier: Development Status :: 4 - Beta
Classifier: Intended Audience :: Developers
Classifier: Topic :: Software Development :: Build Tools
Classifier: Programming Language :: Python :: 2.7
Classifier: Programming Language :: Python :: 3.3
Classifier: Programming Language :: Python :: 3.4
Classifier: Programming Language :: Python :: 3.5
Classifier: Programming Language :: Python :: 3.6
Classifier: License :: OSI Approved :: GNU General Public License v3 (GPLv3)
Requires-Dist: appdirs
Requires-Dist: packaging (==16.8)
Requires-Dist: pyparsing
Requires-Dist: six (==1.10.0)
Requires-Dist: nose (==1.3.7)
Requires-Dist: nose-testconfig (==0.10)
Requires-Dist: wget
Requires-Dist: pytest
